README.rst
setup.py
djel/__init__.py
djel.egg-info/PKG-INFO
djel.egg-info/SOURCES.txt
djel.egg-info/dependency_links.txt
djel.egg-info/top_level.txt