Metadata-Version: 1.0
Name: djel
Version: 0.1
Summary: collection of Django gel code
Home-page: UNKNOWN
Author: Wil Tan
Author-email: wil@dready.org
License: MIT/X
Platform: UNKNOWN
